odoo/addons/web_widget_url_advanced/README.rst
odoo/addons/web_widget_url_advanced/__init__.py
odoo/addons/web_widget_url_advanced/__manifest__.py
odoo/addons/web_widget_url_advanced/i18n/es.po
odoo/addons/web_widget_url_advanced/i18n/web_widget_url_advanced.pot
odoo/addons/web_widget_url_advanced/i18n/zh_CN.po
odoo/addons/web_widget_url_advanced/readme/CONTRIBUTORS.rst
odoo/addons/web_widget_url_advanced/readme/DESCRIPTION.rst
odoo/addons/web_widget_url_advanced/readme/ROADMAP.rst
odoo/addons/web_widget_url_advanced/readme/USAGE.rst
odoo/addons/web_widget_url_advanced/static/description/after.png
odoo/addons/web_widget_url_advanced/static/description/before.png
odoo/addons/web_widget_url_advanced/static/description/icon.png
odoo/addons/web_widget_url_advanced/static/description/index.html
odoo/addons/web_widget_url_advanced/static/src/js/url_widget.js
odoo/addons/web_widget_url_advanced/templates/assets.xml
odoo13_addon_web_widget_url_advanced-13.0.1.1.1.dist-info/METADATA
odoo13_addon_web_widget_url_advanced-13.0.1.1.1.dist-info/WHEEL
odoo13_addon_web_widget_url_advanced-13.0.1.1.1.dist-info/top_level.txt
odoo13_addon_web_widget_url_advanced-13.0.1.1.1.dist-info/RECORD
