Metadata-Version: 2.1
Name: odoo13-addon-web-widget-url-advanced
Version: 13.0.1.1.1
Summary: This module extends URL widget for displaying anchors with custom labels.
Home-page: https://github.com/OCA/web/
Author: Camptocamp, Odoo Community Association (OCA)
Author-email: support@odoo-community.org
License: LGPL-3
Platform: UNKNOWN
Classifier: Programming Language :: Python
Classifier: Framework :: Odoo
Classifier: License :: OSI Approved :: GNU Lesser General Public License v3 (LGPLv3)
Requires-Python: >=3.5
Requires-Dist: odoo (<13.1dev,>=13.0a)
